htmltools/__init__.py
htmltools/entities.py
htmltools_hcn1z1-0.0.2.dist-info/LICENSE
htmltools_hcn1z1-0.0.2.dist-info/METADATA
htmltools_hcn1z1-0.0.2.dist-info/WHEEL
htmltools_hcn1z1-0.0.2.dist-info/top_level.txt
htmltools_hcn1z1-0.0.2.dist-info/RECORD
