Metadata-Version: 2.1
Name: htmltools-hcn1z1
Version: 0.0.2
Summary: A small package to convert html file to entities
Home-page: https://github.com/hcn1z1/html-entities
Author: Mohamed Amine Hammane
Author-email: mohamedhamma2003@gmail.com
License: UNKNOWN
Project-URL: Bug Tracker, https://github.com/hcn1z1/html-entities/issues
Platform: UNKNOWN
Classifier: Programming Language :: Python :: 3
Classifier: License :: OSI Approved :: MIT License
Classifier: Operating System :: OS Independent
Requires-Python: >=3.4
License-File: LICENSE
